hs3/__init__.py
hs3/diff.py
hs3/graphml.py
hs3-1.0.2.data/scripts/hs3diff
hs3-1.0.2.data/scripts/hs3tographml
hs3-1.0.2.dist-info/LICENSE
hs3-1.0.2.dist-info/METADATA
hs3-1.0.2.dist-info/WHEEL
hs3-1.0.2.dist-info/top_level.txt
hs3-1.0.2.dist-info/RECORD
