Metadata-Version: 2.1
Name: hs3
Version: 1.0.2
Summary: Utilities for the HS3 standard in high-energy physics
Home-page: https://github.com/hep-statistics-serialization-standard/python-hep-statistics-serialization-standard/tree/master
Author: Carsten Burgard
Author-email: cburgard@cern.ch
License: BSD-3-Clause
Classifier: Programming Language :: Python :: 3
Classifier: License :: OSI Approved :: BSD License
Classifier: Operating System :: OS Independent
Requires-Python: >=3.6
License-File: LICENSE
